pybaseballstats/__init__.py
pybaseballstats/bref_draft.py
pybaseballstats/bref_managers.py
pybaseballstats/bref_single_player.py
pybaseballstats/fangraphs_single_game.py
pybaseballstats/retrosheet.py
pybaseballstats/statcast.py
pybaseballstats/statcast_single_game.py
pybaseballstats/umpire_scorecards.py
pybaseballstats/consts/__init__.py
pybaseballstats/consts/bref_consts.py
pybaseballstats/consts/fangraphs_consts.py
pybaseballstats/consts/retrosheet_consts.py
pybaseballstats/consts/statcast_consts.py
pybaseballstats/consts/statcast_leaderboard_consts.py
pybaseballstats/consts/umpire_scorecard_consts.py
pybaseballstats/utils/__init__.py
pybaseballstats/utils/bref_utils.py
pybaseballstats/utils/fangraphs_utils.py
pybaseballstats/utils/retrosheet_utils.py
pybaseballstats/utils/statcast_utils.py
pybaseballstats-0.4.5.dist-info/licenses/LICENSE
pybaseballstats-0.4.5.dist-info/METADATA
pybaseballstats-0.4.5.dist-info/WHEEL
pybaseballstats-0.4.5.dist-info/top_level.txt
pybaseballstats-0.4.5.dist-info/RECORD
