Metadata-Version: 2.4
Name: pybaseballstats
Version: 0.4.5
Summary: A Python package for scraping baseball data.
Author-email: Nicolas Carbone <carbone.nicolas0@gmail.com>
Maintainer-email: Nicolas Carbone <carbone.nicolas0@gmail.com>
License: MIT
Project-URL: Repository, https://github.com/nico671/pybaseballstats
Keywords: baseball,stats,data,savant,Baseball Savant,Fangraphs,MLB,scraping,sabermetrics
Classifier: Development Status :: 4 - Beta
Classifier: Intended Audience :: Developers
Requires-Python: >=3.11
License-File: LICENSE
Requires-Dist: aiohttp>=3.11.11
Requires-Dist: bs4>=0.0.2
Requires-Dist: curl-cffi>=0.13.0
Requires-Dist: dateparser>=1.2.1
Requires-Dist: nest-asyncio>=1.6.0
Requires-Dist: playwright>=1.55.0
Requires-Dist: polars>=1.20.0
Requires-Dist: rapidfuzz>=3.14.3
Requires-Dist: requests>=2.32.3
Requires-Dist: rich>=14.0.0
Requires-Dist: unidecode>=1.3.8
Dynamic: license-file
